srwlpy.cp38-win_amd64.pyd
oasys_srw/__init__.py
oasys_srw/srwl_bl.py
oasys_srw/srwl_uti_brightness.py
oasys_srw/srwl_uti_cryst.py
oasys_srw/srwl_uti_mag.py
oasys_srw/srwl_uti_smp.py
oasys_srw/srwl_uti_smp_rnd_obj2d.py
oasys_srw/srwl_uti_src.py
oasys_srw/srwl_uti_und.py
oasys_srw/srwlib.py
oasys_srw/uti_io.py
oasys_srw/uti_io_genesis.py
oasys_srw/uti_math.py
oasys_srw/uti_parse.py
oasys_srw/uti_plot.py
oasys_srw/uti_plot_com.py
oasys_srw/uti_plot_matplotlib.py
oasys_srwpy-1.0.5.data/data/libfftw3-3.dll
oasys_srwpy-1.0.5.data/data/libfftw3f-3.dll
oasys_srwpy-1.0.5.data/data/libfftw3l-3.dll
oasys_srwpy-1.0.5.dist-info/AUTHORS.rst
oasys_srwpy-1.0.5.dist-info/LICENSE
oasys_srwpy-1.0.5.dist-info/METADATA
oasys_srwpy-1.0.5.dist-info/WHEEL
oasys_srwpy-1.0.5.dist-info/top_level.txt
oasys_srwpy-1.0.5.dist-info/RECORD
