Metadata-Version: 2.1
Name: oasys-srwpy
Version: 1.0.5
Summary: Synchrotron Radiation Workshop
Home-page: https://github.com/oasys-kit/srwpy
Author: European Synchrotron Radiation Facility
Author-email: srio@esrf.eu
License: BSD (3-clause)
Classifier: Development Status :: 2 - Pre-Alpha
Classifier: Natural Language :: English
Classifier: Programming Language :: Python :: 3
Classifier: Operating System :: POSIX :: Linux
Classifier: Operating System :: MacOS :: MacOS X
Classifier: Operating System :: Microsoft :: Windows
License-File: LICENSE
License-File: AUTHORS.rst
Requires-Dist: matplotlib
Requires-Dist: numpy
Requires-Dist: pillow
Requires-Dist: scipy
